LICENSE
MANIFEST.in
README.rst
setup.cfg
setup.py
clipwdmgr/__init__.py
clipwdmgr/__main__.py
clipwdmgr/clipwdmgr.py
clipwdmgr/common.py
clipwdmgr/crypto.py
clipwdmgr/database.py
clipwdmgr/globals.py
clipwdmgr.egg-info/PKG-INFO
clipwdmgr.egg-info/SOURCES.txt
clipwdmgr.egg-info/dependency_links.txt
clipwdmgr.egg-info/entry_points.txt
clipwdmgr.egg-info/requires.txt
clipwdmgr.egg-info/top_level.txt