Metadata-Version: 1.1
Name: clipwdmgr
Version: 0.11
Summary: Command Line Password Manager.
Home-page: https://github.com/samisalkosuo/clipasswordmgr
Author: Sami Salkosuo
Author-email: dev@rnd-dev.com
License: MIT
Platform: UNKNOWN
Classifier: Development Status :: 4 - Beta
Classifier: Intended Audience :: Developers
Classifier: Intended Audience :: End Users/Desktop
Classifier: Environment :: Console
Classifier: License :: OSI Approved :: MIT License
Classifier: Natural Language :: English
Classifier: Operating System :: OS Independent
Classifier: Programming Language :: Python :: 3.4
Classifier: Programming Language :: Python :: 3.5
Classifier: Programming Language :: Python :: 3 :: Only
Classifier: Topic :: Security
Classifier: Topic :: Utilities
